anticord/AntiCordGateway.py
anticord/AntiCordPlainHttpRequest.py
anticord/__init__.py
Anticord-0.4.dist-info/LICENSE.txt
Anticord-0.4.dist-info/METADATA
Anticord-0.4.dist-info/WHEEL
Anticord-0.4.dist-info/top_level.txt
Anticord-0.4.dist-info/RECORD
