Metadata-Version: 2.1
Name: Anticord
Version: 0.4
Summary: Discord api wrapper
Author: Spiderman from earth 69
Author-email: spidermanfromearth69@gmail.com
License-File: LICENSE.txt
Requires-Dist: websocket
Requires-Dist: requests
